checktools/__init__.py
checktools/local_route_test.py
checktools/update_task_versions.py
createtools/__init__.py
createtools/module-template/module-name.wdl
createtools/module-template/test.json
createtools/module-template/test.sh
createtools/pipeline-template/pipeline-name.wdl
createtools/pipeline-template/test.json
createtools/pipeline-template/test.sh
createtools/task-template/task-name.wdl
createtools/task-template/test.json
createtools/task-template/test.sh
gittools/__init__.py
gittools/wdl_tagger.py
gittools/test/__init__.py
iseqwdltools-0.1.5.data/scripts/convert-wdl
iseqwdltools-0.1.5.data/scripts/create-module
iseqwdltools-0.1.5.data/scripts/create-pipeline
iseqwdltools-0.1.5.data/scripts/create-task
iseqwdltools-0.1.5.data/scripts/fixer.rb
iseqwdltools-0.1.5.data/scripts/full-static-analysis
iseqwdltools-0.1.5.data/scripts/source-target-branch-warn
iseqwdltools-0.1.5.data/scripts/suffix
iseqwdltools-0.1.5.data/scripts/upload
iseqwdltools-0.1.5.data/scripts/wdltools-analysis
iseqwdltools-0.1.5.data/scripts/womtool-analysis
iseqwdltools-0.1.5.dist-info/LICENSE
iseqwdltools-0.1.5.dist-info/METADATA
iseqwdltools-0.1.5.dist-info/WHEEL
iseqwdltools-0.1.5.dist-info/entry_points.txt
iseqwdltools-0.1.5.dist-info/top_level.txt
iseqwdltools-0.1.5.dist-info/RECORD
