Metadata-Version: 2.1
Name: iseqwdltools
Version: 0.1.5
Summary: Meta data for intelliseq
Home-page: https://gitlab.com/intelliseq/iseqmetatools
Author: motfalo
Author-email: olaf.tomaszewski@intelliseq.pl
Classifier: Programming Language :: Python :: 3
Classifier: License :: Free for non-commercial use
Classifier: Operating System :: OS Independent
Requires-Python: >=3.6
License-File: LICENSE
Requires-Dist: gitpython >=3.1.30
Requires-Dist: packaging >=22.0
Requires-Dist: pytest >=6.0.0
